gemini_structurizer/__init__.py
gemini_structurizer/processor.py
gemini_structurizer-0.1.8.dist-info/licenses/LICENSE
gemini_structurizer-0.1.8.dist-info/METADATA
gemini_structurizer-0.1.8.dist-info/WHEEL
gemini_structurizer-0.1.8.dist-info/entry_points.txt
gemini_structurizer-0.1.8.dist-info/top_level.txt
gemini_structurizer-0.1.8.dist-info/RECORD
