Metadata-Version: 2.4
Name: gemini-structurizer
Version: 0.1.8
Summary: A tool that uses the Gemini API to convert files into structured JSON.
Author-email: zhanngpenng <zhanngpenng@gmail.com>
License: MIT License
Classifier: Programming Language :: Python :: 3
Classifier: License :: OSI Approved :: MIT License
Classifier: Operating System :: OS Independent
Classifier: Topic :: Software Development :: Libraries :: Python Modules
Classifier: Topic :: Utilities
Classifier: Intended Audience :: Developers
Requires-Python: >=3.9.21
License-File: LICENSE
Requires-Dist: google-genai>=1.20.0
Requires-Dist: PyYAML>=6.0
Dynamic: license-file
